messages_sender/__init__.py
messages_sender/__version__.py
messages_sender/senders.py
messages_sender/smtp.py
messages_sender/telegram.py
messages_sender-0.1.3.dist-info/LICENSE.md
messages_sender-0.1.3.dist-info/WHEEL
messages_sender-0.1.3.dist-info/METADATA
messages_sender-0.1.3.dist-info/RECORD
